round_utils/__init__.py
round_utils/round.py
round_utils-2.0.1.dist-info/LICENSE
round_utils-2.0.1.dist-info/METADATA
round_utils-2.0.1.dist-info/WHEEL
round_utils-2.0.1.dist-info/top_level.txt
round_utils-2.0.1.dist-info/RECORD
