Metadata-Version: 2.1
Name: round-utils
Version: 2.0.1
Summary: Package for rounding functions
Home-page: https://github.com/IliyaZinoviev/round-utils.git
Author: Marchenko Ilya
Author-email: mrmar333@yandex.ru
License: MIT
Keywords: round,utils,number
Platform: any
Classifier: Intended Audience :: Developers
Classifier: License :: OSI Approved :: MIT License
Classifier: Programming Language :: Python
Classifier: Programming Language :: Python :: 3.8
Classifier: Operating System :: OS Independent
Requires-Python: >=3.8
